manganite/__init__.py
manganite/cell_manager.py
manganite/command.py
manganite/file_picker.py
manganite/grid.py
manganite/jupyter.py
manganite/magics.py
manganite/preprocessor.py
manganite-0.0.5.data/data/etc/jupyter/jupyter_server_config.d/manganite.json
manganite-0.0.5.dist-info/LICENSE
manganite-0.0.5.dist-info/METADATA
manganite-0.0.5.dist-info/WHEEL
manganite-0.0.5.dist-info/entry_points.txt
manganite-0.0.5.dist-info/top_level.txt
manganite-0.0.5.dist-info/RECORD
