Metadata-Version: 2.1
Name: manganite
Version: 0.0.5
Summary: Dashboarding tool built on the powerful Panel framework.
Author-email: Hubert Kosiacki <hubert@kosiacki.com>, Daniel Dobos <danielandras.dobos@gmail.com>, Nils Lohndorf <nils@loehndorf.com>
Project-URL: Homepage, https://github.com/LCL-CAVE/manganite
Project-URL: Bug Tracker, https://github.com/LCL-CAVE/manganite/issues
Requires-Python: >=3.8
License-File: LICENSE
Requires-Dist: ast-scope
Requires-Dist: nbconvert
Requires-Dist: panel >=1.2
Requires-Dist: param ==1.13.0
Requires-Dist: pathvalidate >=3.1.0
Requires-Dist: jupyter-bokeh >=3.0.7
